bbfcapi/__init__.py
bbfcapi/api_async.py
bbfcapi/api_sync.py
bbfcapi/app.py
bbfcapi/client_async.py
bbfcapi/client_common.py
bbfcapi/client_sync.py
bbfcapi/lib_async.py
bbfcapi/lib_sync.py
bbfcapi/parser.py
bbfcapi/types.py
bbfcapi-3.0.1.dist-info/LICENSE
bbfcapi-3.0.1.dist-info/WHEEL
bbfcapi-3.0.1.dist-info/METADATA
bbfcapi-3.0.1.dist-info/RECORD
