Metadata-Version: 2.1
Name: bbfcapi
Version: 3.0.1
Summary: API service, library and parser for BBFC
Home-page: https://github.com/Fustra/bbfcapi/
License: AGPL-3.0
Author: QasimK
Author-email: noreply@QasimK.io
Requires-Python: >=3.8,<4.0
Classifier: License :: OSI Approved :: GNU Affero General Public License v3
Classifier: Programming Language :: Python :: 3
Classifier: Programming Language :: Python :: 3.8
Classifier: Programming Language :: Python :: 3.9
Provides-Extra: all
Provides-Extra: api_async
Provides-Extra: api_sync
Provides-Extra: app
Provides-Extra: client_async
Provides-Extra: client_sync
Provides-Extra: lib_async
Provides-Extra: lib_sync
Requires-Dist: aiohttp[speedups] (>=3.6,<4.0); extra == "client_async" or extra == "lib_async" or extra == "app" or extra == "api_async" or extra == "all"
Requires-Dist: fastapi (>=0.63.0,<0.64.0); extra == "app" or extra == "all"
Requires-Dist: pydantic (>=1.4,<2.0)
Requires-Dist: pyhumps (>=1.3.1,<2.0.0); extra == "app" or extra == "api_async" or extra == "api_sync" or extra == "all"
Requires-Dist: requests (>=2.24,<3.0); extra == "client_sync" or extra == "lib_sync" or extra == "api_sync" or extra == "all"
Requires-Dist: uvicorn (>=0.13.4,<0.14.0); extra == "app" or extra == "all"
Project-URL: Repository, https://github.com/Fustra/bbfcapi/
